cbi_storages/__init__.py
tests/__init__.py
cbi_storages-1.0.0.dist-info/LICENSE
cbi_storages-1.0.0.dist-info/METADATA
cbi_storages-1.0.0.dist-info/WHEEL
cbi_storages-1.0.0.dist-info/top_level.txt
cbi_storages-1.0.0.dist-info/zip-safe
cbi_storages-1.0.0.dist-info/RECORD
